odoo/addons/monitoring/README.rst
odoo/addons/monitoring/__init__.py
odoo/addons/monitoring/__manifest__.py
odoo/addons/monitoring/controllers/__init__.py
odoo/addons/monitoring/controllers/main.py
odoo/addons/monitoring/data/ir_cron.xml
odoo/addons/monitoring/demo/demo_data.xml
odoo/addons/monitoring/i18n/monitoring.pot
odoo/addons/monitoring/models/__init__.py
odoo/addons/monitoring/models/monitoring.py
odoo/addons/monitoring/models/monitoring_script.py
odoo/addons/monitoring/readme/CONTRIBUTORS.rst
odoo/addons/monitoring/readme/DESCRIPTION.rst
odoo/addons/monitoring/readme/USAGE.rst
odoo/addons/monitoring/security/ir.model.access.csv
odoo/addons/monitoring/static/description/icon.png
odoo/addons/monitoring/static/description/index.html
odoo/addons/monitoring/tests/__init__.py
odoo/addons/monitoring/tests/test_monitoring.py
odoo/addons/monitoring/views/menuitems.xml
odoo/addons/monitoring/views/monitoring_script_views.xml
odoo/addons/monitoring/views/monitoring_views.xml
odoo_addon_monitoring-15.0.1.0.0.2.dist-info/METADATA
odoo_addon_monitoring-15.0.1.0.0.2.dist-info/WHEEL
odoo_addon_monitoring-15.0.1.0.0.2.dist-info/top_level.txt
odoo_addon_monitoring-15.0.1.0.0.2.dist-info/RECORD
